undcli/__init__.py
undcli/commands/__init__.py
undcli/commands/env.py
undcli/commands/storage.py
undcli/main.py
undcli/utils.py
undcli-1.0.6.dist-info/entry_points.txt
undcli-1.0.6.dist-info/WHEEL
undcli-1.0.6.dist-info/METADATA
undcli-1.0.6.dist-info/RECORD
