Metadata-Version: 2.1
Name: undcli
Version: 1.0.6
Summary: 
Author: Aayushman Choudhary
Author-email: aayushmanchaudhory@gmail.com
Requires-Python: >=3.10,<4.0
Classifier: Programming Language :: Python :: 3
Requires-Dist: boto3 (>=1.28.60,<2.0.0)
Requires-Dist: google-cloud-storage (>=2.11.0,<3.0.0)
Requires-Dist: tqdm (>=4.66.1,<5.0.0)
Requires-Dist: typer[all] (>=0.9.0,<0.10.0)
